{
  "results": {
    "seed_42_n512": {
      "resnet18": {
        "cka": 0.02037872187793255,
        "acc": 71.5
      },
      "resnet34": {
        "cka": 0.020088685676455498,
        "acc": 75.1
      },
      "resnet50": {
        "cka": 0.021218884736299515,
        "acc": 79.8
      },
      "resnet101": {
        "cka": 0.022467926144599915,
        "acc": 81.5
      },
      "resnet152": {
        "cka": 0.01761668547987938,
        "acc": 82.0
      },
      "resnext50_32x4d": {
        "cka": 0.02025545760989189,
        "acc": 80.1
      },
      "resnext101_32x8d": {
        "cka": 0.018869254738092422,
        "acc": 82.2
      },
      "wide_resnet50_2": {
        "cka": 0.024743402376770973,
        "acc": 81.6
      },
      "wide_resnet101_2": {
        "cka": 0.03192313015460968,
        "acc": 82.5
      },
      "densenet121": {
        "cka": 0.021762801334261894,
        "acc": 75.6
      },
      "densenet169": {
        "cka": 0.032567836344242096,
        "acc": 76.2
      },
      "densenet201": {
        "cka": 0.026395119726657867,
        "acc": 77.4
      },
      "efficientnet_b0": {
        "cka": 0.0306993555277586,
        "acc": 77.7
      },
      "efficientnet_b1": {
        "cka": 0.022314727306365967,
        "acc": 79.2
      },
      "efficientnet_b2": {
        "cka": 0.015479528345167637,
        "acc": 80.6
      },
      "efficientnet_b3": {
        "cka": 0.02087758481502533,
        "acc": 82.0
      },
      "efficientnet_b4": {
        "cka": 0.025347691029310226,
        "acc": 83.4
      },
      "efficientnetv2_s": {
        "cka": 0.012924165464937687,
        "acc": 83.9
      },
      "efficientnetv2_m": {
        "cka": 0.019755857065320015,
        "acc": 85.1
      },
      "mobilenetv2_100": {
        "cka": 0.018021605908870697,
        "acc": 72.9
      },
      "mobilenetv2_140": {
        "cka": 0.0305949617177248,
        "acc": 76.5
      },
      "mobilenetv3_large": {
        "cka": 0.014627531170845032,
        "acc": 75.8
      },
      "mobilenetv3_small": {
        "cka": 0.017562858760356903,
        "acc": 67.7
      },
      "mnasnet_100": {
        "cka": 0.02046145685017109,
        "acc": 74.7
      },
      "convnext_tiny": {
        "cka": 0.016004953533411026,
        "acc": 82.1
      },
      "convnext_small": {
        "cka": 0.013084247708320618,
        "acc": 83.1
      },
      "convnext_base": {
        "cka": 0.014340764842927456,
        "acc": 83.8
      },
      "convnext_large": {
        "cka": 0.017523562535643578,
        "acc": 84.3
      },
      "convnextv2_tiny": {
        "cka": 0.01791233941912651,
        "acc": 82.9
      },
      "convnextv2_base": {
        "cka": 0.015400604344904423,
        "acc": 84.9
      },
      "vit_tiny_patch16": {
        "cka": 0.016094595193862915,
        "acc": 75.5
      },
      "vit_small_patch16": {
        "cka": 0.018948089331388474,
        "acc": 81.4
      },
      "vit_base_patch16": {
        "cka": 0.02116774208843708,
        "acc": 84.0
      },
      "vit_base_patch32": {
        "cka": 0.013901976868510246,
        "acc": 80.7
      },
      "vit_large_patch16": {
        "cka": 0.020710740238428116,
        "acc": 85.8
      },
      "vit_small_patch16_dino": {
        "cka": 0.03179898485541344,
        "acc": 78.0
      },
      "swin_tiny": {
        "cka": 0.012480191886425018,
        "acc": 81.2
      },
      "swin_small": {
        "cka": 0.019986113533377647,
        "acc": 83.2
      },
      "swin_base": {
        "cka": 0.014940918423235416,
        "acc": 83.5
      },
      "deit_tiny": {
        "cka": 0.02199263870716095,
        "acc": 72.2
      },
      "deit_small": {
        "cka": 0.015737485140562057,
        "acc": 79.9
      },
      "deit_base": {
        "cka": 0.017002522945404053,
        "acc": 81.8
      },
      "deit3_small": {
        "cka": 0.030849482864141464,
        "acc": 81.4
      },
      "deit3_base": {
        "cka": 0.018420258536934853,
        "acc": 83.8
      },
      "deit3_large": {
        "cka": 0.010395008139312267,
        "acc": 84.9
      },
      "regnetx_016": {
        "cka": 0.025809505954384804,
        "acc": 73.0
      },
      "regnetx_032": {
        "cka": 0.0313461497426033,
        "acc": 75.2
      },
      "regnetx_064": {
        "cka": 0.035275887697935104,
        "acc": 76.4
      },
      "regnetx_160": {
        "cka": 0.03432244434952736,
        "acc": 79.7
      },
      "regnety_016": {
        "cka": 0.026835544034838676,
        "acc": 74.0
      },
      "regnety_032": {
        "cka": 0.01663876883685589,
        "acc": 76.6
      },
      "regnety_064": {
        "cka": 0.02232913300395012,
        "acc": 77.2
      },
      "regnety_160": {
        "cka": 0.022728921845555305,
        "acc": 80.4
      },
      "maxvit_tiny": {
        "cka": 0.019316304475069046,
        "acc": 83.4
      },
      "maxvit_small": {
        "cka": 0.013467988930642605,
        "acc": 84.5
      },
      "coatnet_0": {
        "cka": 0.013118909671902657,
        "acc": 82.4
      },
      "efficientformer_l1": {
        "cka": 0.02571428008377552,
        "acc": 80.2
      },
      "efficientformer_l3": {
        "cka": 0.010386069305241108,
        "acc": 82.4
      },
      "efficientformer_l7": {
        "cka": 0.018447453156113625,
        "acc": 83.3
      },
      "edgenext_small": {
        "cka": 0.022056125104427338,
        "acc": 81.1
      },
      "edgenext_base": {
        "cka": 0.02129664085805416,
        "acc": 83.3
      },
      "inception_v3": {
        "cka": 0.043994709849357605,
        "acc": 77.3
      },
      "inception_v4": {
        "cka": 0.02483861893415451,
        "acc": 80.2
      },
      "dpn68": {
        "cka": 0.025420689955353737,
        "acc": 76.3
      },
      "dpn92": {
        "cka": 0.022923054173588753,
        "acc": 79.5
      },
      "dpn131": {
        "cka": 0.019848693162202835,
        "acc": 79.8
      },
      "nasnetalarge": {
        "cka": 0.024077314883470535,
        "acc": 82.6
      },
      "senet154": {
        "cka": 0.025836879387497902,
        "acc": 81.3
      },
      "seresnext50_32x4d": {
        "cka": 0.02677467279136181,
        "acc": 79.9
      },
      "res2net50_26w_4s": {
        "cka": 0.022802172228693962,
        "acc": 78.0
      },
      "res2net101_26w_4s": {
        "cka": 0.020312365144491196,
        "acc": 79.2
      },
      "hrnet_w18": {
        "cka": 0.028016982600092888,
        "acc": 78.0
      },
      "hrnet_w32": {
        "cka": 0.03070608526468277,
        "acc": 78.4
      },
      "hrnet_w48": {
        "cka": 0.027048885822296143,
        "acc": 79.3
      },
      "ghostnet_100": {
        "cka": 0.01966889388859272,
        "acc": 74.0
      },
      "poolformer_s12": {
        "cka": 0.008277215994894505,
        "acc": 77.2
      },
      "poolformer_s24": {
        "cka": 0.02377205342054367,
        "acc": 80.3
      },
      "poolformer_s36": {
        "cka": 0.010150606743991375,
        "acc": 81.4
      },
      "poolformer_m36": {
        "cka": 0.02106691151857376,
        "acc": 82.1
      },
      "cait_s24_224": {
        "cka": 0.01626652479171753,
        "acc": 83.5
      },
      "mixer_b16": {
        "cka": 0.022022878751158714,
        "acc": 78.5
      },
      "vgg16_bn": {
        "cka": 0.03776894509792328,
        "acc": 73.4
      },
      "vgg19_bn": {
        "cka": 0.03851216286420822,
        "acc": 74.2
      }
    },
    "seed_123_n512": {
      "resnet18": {
        "cka": 0.032985296100378036,
        "acc": 71.5
      },
      "resnet34": {
        "cka": 0.0203752089291811,
        "acc": 75.1
      },
      "resnet50": {
        "cka": 0.01768082194030285,
        "acc": 79.8
      },
      "resnet101": {
        "cka": 0.02103583514690399,
        "acc": 81.5
      },
      "resnet152": {
        "cka": 0.021564163267612457,
        "acc": 82.0
      },
      "resnext50_32x4d": {
        "cka": 0.022897185757756233,
        "acc": 80.1
      },
      "resnext101_32x8d": {
        "cka": 0.02660016529262066,
        "acc": 82.2
      },
      "wide_resnet50_2": {
        "cka": 0.0248582661151886,
        "acc": 81.6
      },
      "wide_resnet101_2": {
        "cka": 0.029391655698418617,
        "acc": 82.5
      },
      "densenet121": {
        "cka": 0.023288391530513763,
        "acc": 75.6
      },
      "densenet169": {
        "cka": 0.03827536106109619,
        "acc": 76.2
      },
      "densenet201": {
        "cka": 0.029261186718940735,
        "acc": 77.4
      },
      "efficientnet_b0": {
        "cka": 0.023991916328668594,
        "acc": 77.7
      },
      "efficientnet_b1": {
        "cka": 0.023750578984618187,
        "acc": 79.2
      },
      "efficientnet_b2": {
        "cka": 0.014975432306528091,
        "acc": 80.6
      },
      "efficientnet_b3": {
        "cka": 0.013408350758254528,
        "acc": 82.0
      },
      "efficientnet_b4": {
        "cka": 0.027316411957144737,
        "acc": 83.4
      },
      "efficientnetv2_s": {
        "cka": 0.013846135698258877,
        "acc": 83.9
      },
      "efficientnetv2_m": {
        "cka": 0.02030898444354534,
        "acc": 85.1
      },
      "mobilenetv2_100": {
        "cka": 0.018190007656812668,
        "acc": 72.9
      },
      "mobilenetv2_140": {
        "cka": 0.03226441517472267,
        "acc": 76.5
      },
      "mobilenetv3_large": {
        "cka": 0.01801432855427265,
        "acc": 75.8
      },
      "mobilenetv3_small": {
        "cka": 0.02076416276395321,
        "acc": 67.7
      },
      "mnasnet_100": {
        "cka": 0.026254337280988693,
        "acc": 74.7
      },
      "convnext_tiny": {
        "cka": 0.02087223529815674,
        "acc": 82.1
      },
      "convnext_small": {
        "cka": 0.012203632853925228,
        "acc": 83.1
      },
      "convnext_base": {
        "cka": 0.029500357806682587,
        "acc": 83.8
      },
      "convnext_large": {
        "cka": 0.01577787473797798,
        "acc": 84.3
      },
      "convnextv2_tiny": {
        "cka": 0.02273695357143879,
        "acc": 82.9
      },
      "convnextv2_base": {
        "cka": 0.019264793023467064,
        "acc": 84.9
      },
      "vit_tiny_patch16": {
        "cka": 0.020979154855012894,
        "acc": 75.5
      },
      "vit_small_patch16": {
        "cka": 0.015175980515778065,
        "acc": 81.4
      },
      "vit_base_patch16": {
        "cka": 0.020097021013498306,
        "acc": 84.0
      },
      "vit_base_patch32": {
        "cka": 0.01358079630881548,
        "acc": 80.7
      },
      "vit_large_patch16": {
        "cka": 0.022660959511995316,
        "acc": 85.8
      },
      "vit_small_patch16_dino": {
        "cka": 0.03109561651945114,
        "acc": 78.0
      },
      "swin_tiny": {
        "cka": 0.011722649447619915,
        "acc": 81.2
      },
      "swin_small": {
        "cka": 0.015057585202157497,
        "acc": 83.2
      },
      "swin_base": {
        "cka": 0.023499727249145508,
        "acc": 83.5
      },
      "deit_tiny": {
        "cka": 0.020511940121650696,
        "acc": 72.2
      },
      "deit_small": {
        "cka": 0.01681407541036606,
        "acc": 79.9
      },
      "deit_base": {
        "cka": 0.024782799184322357,
        "acc": 81.8
      },
      "deit3_small": {
        "cka": 0.028606737032532692,
        "acc": 81.4
      },
      "deit3_base": {
        "cka": 0.013169598765671253,
        "acc": 83.8
      },
      "deit3_large": {
        "cka": 0.020060651004314423,
        "acc": 84.9
      },
      "regnetx_016": {
        "cka": 0.0267036035656929,
        "acc": 73.0
      },
      "regnetx_032": {
        "cka": 0.041164081543684006,
        "acc": 75.2
      },
      "regnetx_064": {
        "cka": 0.031000735238194466,
        "acc": 76.4
      },
      "regnetx_160": {
        "cka": 0.03327262029051781,
        "acc": 79.7
      },
      "regnety_016": {
        "cka": 0.03104618564248085,
        "acc": 74.0
      },
      "regnety_032": {
        "cka": 0.018746579065918922,
        "acc": 76.6
      },
      "regnety_064": {
        "cka": 0.030530083924531937,
        "acc": 77.2
      },
      "regnety_160": {
        "cka": 0.029038172215223312,
        "acc": 80.4
      },
      "maxvit_tiny": {
        "cka": 0.011128676123917103,
        "acc": 83.4
      },
      "maxvit_small": {
        "cka": 0.012353800237178802,
        "acc": 84.5
      },
      "coatnet_0": {
        "cka": 0.018421459943056107,
        "acc": 82.4
      },
      "efficientformer_l1": {
        "cka": 0.022104887291789055,
        "acc": 80.2
      },
      "efficientformer_l3": {
        "cka": 0.008990921080112457,
        "acc": 82.4
      },
      "efficientformer_l7": {
        "cka": 0.010660300962626934,
        "acc": 83.3
      },
      "edgenext_small": {
        "cka": 0.017213687300682068,
        "acc": 81.1
      },
      "edgenext_base": {
        "cka": 0.02398466132581234,
        "acc": 83.3
      },
      "inception_v3": {
        "cka": 0.043056245893239975,
        "acc": 77.3
      },
      "inception_v4": {
        "cka": 0.0228355024009943,
        "acc": 80.2
      },
      "dpn68": {
        "cka": 0.03232688084244728,
        "acc": 76.3
      },
      "dpn92": {
        "cka": 0.02674134634435177,
        "acc": 79.5
      },
      "dpn131": {
        "cka": 0.025080405175685883,
        "acc": 79.8
      },
      "nasnetalarge": {
        "cka": 0.025981871411204338,
        "acc": 82.6
      },
      "senet154": {
        "cka": 0.02832880988717079,
        "acc": 81.3
      },
      "seresnext50_32x4d": {
        "cka": 0.03270905837416649,
        "acc": 79.9
      },
      "res2net50_26w_4s": {
        "cka": 0.030605066567659378,
        "acc": 78.0
      },
      "res2net101_26w_4s": {
        "cka": 0.022602755576372147,
        "acc": 79.2
      },
      "hrnet_w18": {
        "cka": 0.0273584071546793,
        "acc": 78.0
      },
      "hrnet_w32": {
        "cka": 0.0244009867310524,
        "acc": 78.4
      },
      "hrnet_w48": {
        "cka": 0.02889752760529518,
        "acc": 79.3
      },
      "ghostnet_100": {
        "cka": 0.01977209560573101,
        "acc": 74.0
      },
      "poolformer_s12": {
        "cka": 0.007251030299812555,
        "acc": 77.2
      },
      "poolformer_s24": {
        "cka": 0.021564876660704613,
        "acc": 80.3
      },
      "poolformer_s36": {
        "cka": 0.009812942706048489,
        "acc": 81.4
      },
      "poolformer_m36": {
        "cka": 0.02434627339243889,
        "acc": 82.1
      },
      "cait_s24_224": {
        "cka": 0.017493626102805138,
        "acc": 83.5
      },
      "mixer_b16": {
        "cka": 0.023501764982938766,
        "acc": 78.5
      },
      "vgg16_bn": {
        "cka": 0.04311817139387131,
        "acc": 73.4
      },
      "vgg19_bn": {
        "cka": 0.042497843503952026,
        "acc": 74.2
      }
    },
    "seed_456_n512": {
      "resnet18": {
        "cka": 0.023684842512011528,
        "acc": 71.5
      },
      "resnet34": {
        "cka": 0.024515336379408836,
        "acc": 75.1
      },
      "resnet50": {
        "cka": 0.02342008613049984,
        "acc": 79.8
      },
      "resnet101": {
        "cka": 0.020743729546666145,
        "acc": 81.5
      },
      "resnet152": {
        "cka": 0.019526677206158638,
        "acc": 82.0
      },
      "resnext50_32x4d": {
        "cka": 0.022686922922730446,
        "acc": 80.1
      },
      "resnext101_32x8d": {
        "cka": 0.02372356504201889,
        "acc": 82.2
      },
      "wide_resnet50_2": {
        "cka": 0.02367483824491501,
        "acc": 81.6
      },
      "wide_resnet101_2": {
        "cka": 0.03335239365696907,
        "acc": 82.5
      },
      "densenet121": {
        "cka": 0.022339455783367157,
        "acc": 75.6
      },
      "densenet169": {
        "cka": 0.032441750168800354,
        "acc": 76.2
      },
      "densenet201": {
        "cka": 0.027974823489785194,
        "acc": 77.4
      },
      "efficientnet_b0": {
        "cka": 0.01946631819009781,
        "acc": 77.7
      },
      "efficientnet_b1": {
        "cka": 0.020811228081583977,
        "acc": 79.2
      },
      "efficientnet_b2": {
        "cka": 0.01833365112543106,
        "acc": 80.6
      },
      "efficientnet_b3": {
        "cka": 0.012663018889725208,
        "acc": 82.0
      },
      "efficientnet_b4": {
        "cka": 0.029098819941282272,
        "acc": 83.4
      },
      "efficientnetv2_s": {
        "cka": 0.010646836832165718,
        "acc": 83.9
      },
      "efficientnetv2_m": {
        "cka": 0.018245602026581764,
        "acc": 85.1
      },
      "mobilenetv2_100": {
        "cka": 0.021482620388269424,
        "acc": 72.9
      },
      "mobilenetv2_140": {
        "cka": 0.03748073801398277,
        "acc": 76.5
      },
      "mobilenetv3_large": {
        "cka": 0.02289116568863392,
        "acc": 75.8
      },
      "mobilenetv3_small": {
        "cka": 0.017197927460074425,
        "acc": 67.7
      },
      "mnasnet_100": {
        "cka": 0.02558857947587967,
        "acc": 74.7
      },
      "convnext_tiny": {
        "cka": 0.015954356640577316,
        "acc": 82.1
      },
      "convnext_small": {
        "cka": 0.012076111510396004,
        "acc": 83.1
      },
      "convnext_base": {
        "cka": 0.0099017433822155,
        "acc": 83.8
      },
      "convnext_large": {
        "cka": 0.011808270588517189,
        "acc": 84.3
      },
      "convnextv2_tiny": {
        "cka": 0.017668411135673523,
        "acc": 82.9
      },
      "convnextv2_base": {
        "cka": 0.020699748769402504,
        "acc": 84.9
      },
      "vit_tiny_patch16": {
        "cka": 0.017746640369296074,
        "acc": 75.5
      },
      "vit_small_patch16": {
        "cka": 0.016128074377775192,
        "acc": 81.4
      },
      "vit_base_patch16": {
        "cka": 0.015057056210935116,
        "acc": 84.0
      },
      "vit_base_patch32": {
        "cka": 0.014276797883212566,
        "acc": 80.7
      },
      "vit_large_patch16": {
        "cka": 0.01614311710000038,
        "acc": 85.8
      },
      "vit_small_patch16_dino": {
        "cka": 0.03024366870522499,
        "acc": 78.0
      },
      "swin_tiny": {
        "cka": 0.011353735812008381,
        "acc": 81.2
      },
      "swin_small": {
        "cka": 0.022655170410871506,
        "acc": 83.2
      },
      "swin_base": {
        "cka": 0.014869309030473232,
        "acc": 83.5
      },
      "deit_tiny": {
        "cka": 0.01635495200753212,
        "acc": 72.2
      },
      "deit_small": {
        "cka": 0.01637449488043785,
        "acc": 79.9
      },
      "deit_base": {
        "cka": 0.02399633079767227,
        "acc": 81.8
      },
      "deit3_small": {
        "cka": 0.025628307834267616,
        "acc": 81.4
      },
      "deit3_base": {
        "cka": 0.014088178984820843,
        "acc": 83.8
      },
      "deit3_large": {
        "cka": 0.016901494935154915,
        "acc": 84.9
      },
      "regnetx_016": {
        "cka": 0.03369957581162453,
        "acc": 73.0
      },
      "regnetx_032": {
        "cka": 0.035991962999105453,
        "acc": 75.2
      },
      "regnetx_064": {
        "cka": 0.03085966780781746,
        "acc": 76.4
      },
      "regnetx_160": {
        "cka": 0.033413857221603394,
        "acc": 79.7
      },
      "regnety_016": {
        "cka": 0.031025616452097893,
        "acc": 74.0
      },
      "regnety_032": {
        "cka": 0.02545318193733692,
        "acc": 76.6
      },
      "regnety_064": {
        "cka": 0.02782609313726425,
        "acc": 77.2
      },
      "regnety_160": {
        "cka": 0.025281677022576332,
        "acc": 80.4
      },
      "maxvit_tiny": {
        "cka": 0.013594338670372963,
        "acc": 83.4
      },
      "maxvit_small": {
        "cka": 0.016141822561621666,
        "acc": 84.5
      },
      "coatnet_0": {
        "cka": 0.015435950830578804,
        "acc": 82.4
      },
      "efficientformer_l1": {
        "cka": 0.02340356446802616,
        "acc": 80.2
      },
      "efficientformer_l3": {
        "cka": 0.01625191979110241,
        "acc": 82.4
      },
      "efficientformer_l7": {
        "cka": 0.013950401917099953,
        "acc": 83.3
      },
      "edgenext_small": {
        "cka": 0.019199054688215256,
        "acc": 81.1
      },
      "edgenext_base": {
        "cka": 0.02323785424232483,
        "acc": 83.3
      },
      "inception_v3": {
        "cka": 0.046300847083330154,
        "acc": 77.3
      },
      "inception_v4": {
        "cka": 0.022249141708016396,
        "acc": 80.2
      },
      "dpn68": {
        "cka": 0.02388068288564682,
        "acc": 76.3
      },
      "dpn92": {
        "cka": 0.023001540452241898,
        "acc": 79.5
      },
      "dpn131": {
        "cka": 0.01676815003156662,
        "acc": 79.8
      },
      "nasnetalarge": {
        "cka": 0.023576298728585243,
        "acc": 82.6
      },
      "senet154": {
        "cka": 0.02247065305709839,
        "acc": 81.3
      },
      "seresnext50_32x4d": {
        "cka": 0.02839982509613037,
        "acc": 79.9
      },
      "res2net50_26w_4s": {
        "cka": 0.0239516980946064,
        "acc": 78.0
      },
      "res2net101_26w_4s": {
        "cka": 0.018787536770105362,
        "acc": 79.2
      },
      "hrnet_w18": {
        "cka": 0.030715037137269974,
        "acc": 78.0
      },
      "hrnet_w32": {
        "cka": 0.028235172852873802,
        "acc": 78.4
      },
      "hrnet_w48": {
        "cka": 0.02193901687860489,
        "acc": 79.3
      },
      "ghostnet_100": {
        "cka": 0.015222428366541862,
        "acc": 74.0
      },
      "poolformer_s12": {
        "cka": 0.0038169140461832285,
        "acc": 77.2
      },
      "poolformer_s24": {
        "cka": 0.02244802936911583,
        "acc": 80.3
      },
      "poolformer_s36": {
        "cka": 0.013220807537436485,
        "acc": 81.4
      },
      "poolformer_m36": {
        "cka": 0.021749349310994148,
        "acc": 82.1
      },
      "cait_s24_224": {
        "cka": 0.02188246138393879,
        "acc": 83.5
      },
      "mixer_b16": {
        "cka": 0.020172463729977608,
        "acc": 78.5
      },
      "vgg16_bn": {
        "cka": 0.03773945942521095,
        "acc": 73.4
      },
      "vgg19_bn": {
        "cka": 0.03614475950598717,
        "acc": 74.2
      }
    },
    "seed_789_n512": {
      "resnet18": {
        "cka": 0.02034018002450466,
        "acc": 71.5
      },
      "resnet34": {
        "cka": 0.022800352424383163,
        "acc": 75.1
      },
      "resnet50": {
        "cka": 0.024333573877811432,
        "acc": 79.8
      },
      "resnet101": {
        "cka": 0.020940445363521576,
        "acc": 81.5
      },
      "resnet152": {
        "cka": 0.021507395431399345,
        "acc": 82.0
      },
      "resnext50_32x4d": {
        "cka": 0.02464439906179905,
        "acc": 80.1
      },
      "resnext101_32x8d": {
        "cka": 0.021081769838929176,
        "acc": 82.2
      },
      "wide_resnet50_2": {
        "cka": 0.02420775033533573,
        "acc": 81.6
      },
      "wide_resnet101_2": {
        "cka": 0.030402427539229393,
        "acc": 82.5
      },
      "densenet121": {
        "cka": 0.022793443873524666,
        "acc": 75.6
      },
      "densenet169": {
        "cka": 0.03363966569304466,
        "acc": 76.2
      },
      "densenet201": {
        "cka": 0.029468724504113197,
        "acc": 77.4
      },
      "efficientnet_b0": {
        "cka": 0.019729258492588997,
        "acc": 77.7
      },
      "efficientnet_b1": {
        "cka": 0.019677788019180298,
        "acc": 79.2
      },
      "efficientnet_b2": {
        "cka": 0.018182961270213127,
        "acc": 80.6
      },
      "efficientnet_b3": {
        "cka": 0.017250852659344673,
        "acc": 82.0
      },
      "efficientnet_b4": {
        "cka": 0.022494476288557053,
        "acc": 83.4
      },
      "efficientnetv2_s": {
        "cka": 0.014171936549246311,
        "acc": 83.9
      },
      "efficientnetv2_m": {
        "cka": 0.020762871950864792,
        "acc": 85.1
      },
      "mobilenetv2_100": {
        "cka": 0.02473703771829605,
        "acc": 72.9
      },
      "mobilenetv2_140": {
        "cka": 0.026478732004761696,
        "acc": 76.5
      },
      "mobilenetv3_large": {
        "cka": 0.014396890997886658,
        "acc": 75.8
      },
      "mobilenetv3_small": {
        "cka": 0.013088695704936981,
        "acc": 67.7
      },
      "mnasnet_100": {
        "cka": 0.023909056559205055,
        "acc": 74.7
      },
      "convnext_tiny": {
        "cka": 0.018420517444610596,
        "acc": 82.1
      },
      "convnext_small": {
        "cka": 0.020060541108250618,
        "acc": 83.1
      },
      "convnext_base": {
        "cka": 0.014711310155689716,
        "acc": 83.8
      },
      "convnext_large": {
        "cka": 0.015391107648611069,
        "acc": 84.3
      },
      "convnextv2_tiny": {
        "cka": 0.01989315077662468,
        "acc": 82.9
      },
      "convnextv2_base": {
        "cka": 0.01526824850589037,
        "acc": 84.9
      },
      "vit_tiny_patch16": {
        "cka": 0.01607792265713215,
        "acc": 75.5
      },
      "vit_small_patch16": {
        "cka": 0.018309107050299644,
        "acc": 81.4
      },
      "vit_base_patch16": {
        "cka": 0.016036005690693855,
        "acc": 84.0
      },
      "vit_base_patch32": {
        "cka": 0.012836500070989132,
        "acc": 80.7
      },
      "vit_large_patch16": {
        "cka": 0.017501693218946457,
        "acc": 85.8
      },
      "vit_small_patch16_dino": {
        "cka": 0.026583468541502953,
        "acc": 78.0
      },
      "swin_tiny": {
        "cka": 0.01366865262389183,
        "acc": 81.2
      },
      "swin_small": {
        "cka": 0.016665609553456306,
        "acc": 83.2
      },
      "swin_base": {
        "cka": 0.011725949123501778,
        "acc": 83.5
      },
      "deit_tiny": {
        "cka": 0.0165450070053339,
        "acc": 72.2
      },
      "deit_small": {
        "cka": 0.020533068105578423,
        "acc": 79.9
      },
      "deit_base": {
        "cka": 0.021019956097006798,
        "acc": 81.8
      },
      "deit3_small": {
        "cka": 0.025880834087729454,
        "acc": 81.4
      },
      "deit3_base": {
        "cka": 0.015653247013688087,
        "acc": 83.8
      },
      "deit3_large": {
        "cka": 0.011546984314918518,
        "acc": 84.9
      },
      "regnetx_016": {
        "cka": 0.033137887716293335,
        "acc": 73.0
      },
      "regnetx_032": {
        "cka": 0.038623612374067307,
        "acc": 75.2
      },
      "regnetx_064": {
        "cka": 0.034285929054021835,
        "acc": 76.4
      },
      "regnetx_160": {
        "cka": 0.039302513003349304,
        "acc": 79.7
      },
      "regnety_016": {
        "cka": 0.028810886666178703,
        "acc": 74.0
      },
      "regnety_032": {
        "cka": 0.0188315249979496,
        "acc": 76.6
      },
      "regnety_064": {
        "cka": 0.029825503006577492,
        "acc": 77.2
      },
      "regnety_160": {
        "cka": 0.02266918681561947,
        "acc": 80.4
      },
      "maxvit_tiny": {
        "cka": 0.01927410438656807,
        "acc": 83.4
      },
      "maxvit_small": {
        "cka": 0.013897368684411049,
        "acc": 84.5
      },
      "coatnet_0": {
        "cka": 0.0166636910289526,
        "acc": 82.4
      },
      "efficientformer_l1": {
        "cka": 0.019588356837630272,
        "acc": 80.2
      },
      "efficientformer_l3": {
        "cka": 0.010453780181705952,
        "acc": 82.4
      },
      "efficientformer_l7": {
        "cka": 0.011875237338244915,
        "acc": 83.3
      },
      "edgenext_small": {
        "cka": 0.01969209313392639,
        "acc": 81.1
      },
      "edgenext_base": {
        "cka": 0.026547569781541824,
        "acc": 83.3
      },
      "inception_v3": {
        "cka": 0.041415829211473465,
        "acc": 77.3
      },
      "inception_v4": {
        "cka": 0.024179702624678612,
        "acc": 80.2
      },
      "dpn68": {
        "cka": 0.02153852954506874,
        "acc": 76.3
      },
      "dpn92": {
        "cka": 0.025159500539302826,
        "acc": 79.5
      },
      "dpn131": {
        "cka": 0.02266346663236618,
        "acc": 79.8
      },
      "nasnetalarge": {
        "cka": 0.024872450157999992,
        "acc": 82.6
      },
      "senet154": {
        "cka": 0.02460469864308834,
        "acc": 81.3
      },
      "seresnext50_32x4d": {
        "cka": 0.02879905328154564,
        "acc": 79.9
      },
      "res2net50_26w_4s": {
        "cka": 0.02367822453379631,
        "acc": 78.0
      },
      "res2net101_26w_4s": {
        "cka": 0.02035769820213318,
        "acc": 79.2
      },
      "hrnet_w18": {
        "cka": 0.02733585052192211,
        "acc": 78.0
      },
      "hrnet_w32": {
        "cka": 0.029271479696035385,
        "acc": 78.4
      },
      "hrnet_w48": {
        "cka": 0.022593993693590164,
        "acc": 79.3
      },
      "ghostnet_100": {
        "cka": 0.018920302391052246,
        "acc": 74.0
      },
      "poolformer_s12": {
        "cka": 0.004401024896651506,
        "acc": 77.2
      },
      "poolformer_s24": {
        "cka": 0.022940682247281075,
        "acc": 80.3
      },
      "poolformer_s36": {
        "cka": 0.013308687135577202,
        "acc": 81.4
      },
      "poolformer_m36": {
        "cka": 0.025620633736252785,
        "acc": 82.1
      },
      "cait_s24_224": {
        "cka": 0.019225435331463814,
        "acc": 83.5
      },
      "mixer_b16": {
        "cka": 0.022940997034311295,
        "acc": 78.5
      },
      "vgg16_bn": {
        "cka": 0.042319878935813904,
        "acc": 73.4
      },
      "vgg19_bn": {
        "cka": 0.031078597530722618,
        "acc": 74.2
      }
    },
    "seed_2024_n512": {
      "resnet18": {
        "cka": 0.0192137248814106,
        "acc": 71.5
      },
      "resnet34": {
        "cka": 0.01823074370622635,
        "acc": 75.1
      },
      "resnet50": {
        "cka": 0.02142329327762127,
        "acc": 79.8
      },
      "resnet101": {
        "cka": 0.019620586186647415,
        "acc": 81.5
      },
      "resnet152": {
        "cka": 0.020666252821683884,
        "acc": 82.0
      },
      "resnext50_32x4d": {
        "cka": 0.02532641962170601,
        "acc": 80.1
      },
      "resnext101_32x8d": {
        "cka": 0.020988795906305313,
        "acc": 82.2
      },
      "wide_resnet50_2": {
        "cka": 0.025872450321912766,
        "acc": 81.6
      },
      "wide_resnet101_2": {
        "cka": 0.025704873725771904,
        "acc": 82.5
      },
      "densenet121": {
        "cka": 0.018880803138017654,
        "acc": 75.6
      },
      "densenet169": {
        "cka": 0.03932702913880348,
        "acc": 76.2
      },
      "densenet201": {
        "cka": 0.03071168251335621,
        "acc": 77.4
      },
      "efficientnet_b0": {
        "cka": 0.02278740517795086,
        "acc": 77.7
      },
      "efficientnet_b1": {
        "cka": 0.02507503516972065,
        "acc": 79.2
      },
      "efficientnet_b2": {
        "cka": 0.011506850831210613,
        "acc": 80.6
      },
      "efficientnet_b3": {
        "cka": 0.013638715259730816,
        "acc": 82.0
      },
      "efficientnet_b4": {
        "cka": 0.023262759670615196,
        "acc": 83.4
      },
      "efficientnetv2_s": {
        "cka": 0.014173136092722416,
        "acc": 83.9
      },
      "efficientnetv2_m": {
        "cka": 0.020432651042938232,
        "acc": 85.1
      },
      "mobilenetv2_100": {
        "cka": 0.020307691767811775,
        "acc": 72.9
      },
      "mobilenetv2_140": {
        "cka": 0.02776975929737091,
        "acc": 76.5
      },
      "mobilenetv3_large": {
        "cka": 0.014440546743571758,
        "acc": 75.8
      },
      "mobilenetv3_small": {
        "cka": 0.02101736329495907,
        "acc": 67.7
      },
      "mnasnet_100": {
        "cka": 0.023332105949521065,
        "acc": 74.7
      },
      "convnext_tiny": {
        "cka": 0.011611503548920155,
        "acc": 82.1
      },
      "convnext_small": {
        "cka": 0.0192253477871418,
        "acc": 83.1
      },
      "convnext_base": {
        "cka": 0.012724773958325386,
        "acc": 83.8
      },
      "convnext_large": {
        "cka": 0.011854469776153564,
        "acc": 84.3
      },
      "convnextv2_tiny": {
        "cka": 0.023597776889801025,
        "acc": 82.9
      },
      "convnextv2_base": {
        "cka": 0.02049708366394043,
        "acc": 84.9
      },
      "vit_tiny_patch16": {
        "cka": 0.020280824974179268,
        "acc": 75.5
      },
      "vit_small_patch16": {
        "cka": 0.01757613569498062,
        "acc": 81.4
      },
      "vit_base_patch16": {
        "cka": 0.023309318348765373,
        "acc": 84.0
      },
      "vit_base_patch32": {
        "cka": 0.02408348023891449,
        "acc": 80.7
      },
      "vit_large_patch16": {
        "cka": 0.021304868161678314,
        "acc": 85.8
      },
      "vit_small_patch16_dino": {
        "cka": 0.02806989476084709,
        "acc": 78.0
      },
      "swin_tiny": {
        "cka": 0.01848158799111843,
        "acc": 81.2
      },
      "swin_small": {
        "cka": 0.0184200219810009,
        "acc": 83.2
      },
      "swin_base": {
        "cka": 0.012363424524664879,
        "acc": 83.5
      },
      "deit_tiny": {
        "cka": 0.017348801717162132,
        "acc": 72.2
      },
      "deit_small": {
        "cka": 0.017659328877925873,
        "acc": 79.9
      },
      "deit_base": {
        "cka": 0.015574480406939983,
        "acc": 81.8
      },
      "deit3_small": {
        "cka": 0.025029269978404045,
        "acc": 81.4
      },
      "deit3_base": {
        "cka": 0.011969857849180698,
        "acc": 83.8
      },
      "deit3_large": {
        "cka": 0.012562843970954418,
        "acc": 84.9
      },
      "regnetx_016": {
        "cka": 0.028438229113817215,
        "acc": 73.0
      },
      "regnetx_032": {
        "cka": 0.039857786148786545,
        "acc": 75.2
      },
      "regnetx_064": {
        "cka": 0.031055642291903496,
        "acc": 76.4
      },
      "regnetx_160": {
        "cka": 0.03015698492527008,
        "acc": 79.7
      },
      "regnety_016": {
        "cka": 0.027597391977906227,
        "acc": 74.0
      },
      "regnety_032": {
        "cka": 0.017818916589021683,
        "acc": 76.6
      },
      "regnety_064": {
        "cka": 0.026537567377090454,
        "acc": 77.2
      },
      "regnety_160": {
        "cka": 0.027610909193754196,
        "acc": 80.4
      },
      "maxvit_tiny": {
        "cka": 0.013334039598703384,
        "acc": 83.4
      },
      "maxvit_small": {
        "cka": 0.01248547900468111,
        "acc": 84.5
      },
      "coatnet_0": {
        "cka": 0.018674328923225403,
        "acc": 82.4
      },
      "efficientformer_l1": {
        "cka": 0.022495072335004807,
        "acc": 80.2
      },
      "efficientformer_l3": {
        "cka": 0.011329451575875282,
        "acc": 82.4
      },
      "efficientformer_l7": {
        "cka": 0.011871223337948322,
        "acc": 83.3
      },
      "edgenext_small": {
        "cka": 0.022850513458251953,
        "acc": 81.1
      },
      "edgenext_base": {
        "cka": 0.028408057987689972,
        "acc": 83.3
      },
      "inception_v3": {
        "cka": 0.044283900409936905,
        "acc": 77.3
      },
      "inception_v4": {
        "cka": 0.021718835458159447,
        "acc": 80.2
      },
      "dpn68": {
        "cka": 0.02419903315603733,
        "acc": 76.3
      },
      "dpn92": {
        "cka": 0.02062961459159851,
        "acc": 79.5
      },
      "dpn131": {
        "cka": 0.01937141828238964,
        "acc": 79.8
      },
      "nasnetalarge": {
        "cka": 0.027006028220057487,
        "acc": 82.6
      },
      "senet154": {
        "cka": 0.02570277824997902,
        "acc": 81.3
      },
      "seresnext50_32x4d": {
        "cka": 0.029223818331956863,
        "acc": 79.9
      },
      "res2net50_26w_4s": {
        "cka": 0.023965517058968544,
        "acc": 78.0
      },
      "res2net101_26w_4s": {
        "cka": 0.015629682689905167,
        "acc": 79.2
      },
      "hrnet_w18": {
        "cka": 0.0309325959533453,
        "acc": 78.0
      },
      "hrnet_w32": {
        "cka": 0.029006702825427055,
        "acc": 78.4
      },
      "hrnet_w48": {
        "cka": 0.02215453051030636,
        "acc": 79.3
      },
      "ghostnet_100": {
        "cka": 0.014447200112044811,
        "acc": 74.0
      },
      "poolformer_s12": {
        "cka": 0.005234046373516321,
        "acc": 77.2
      },
      "poolformer_s24": {
        "cka": 0.021363725885748863,
        "acc": 80.3
      },
      "poolformer_s36": {
        "cka": 0.011203734204173088,
        "acc": 81.4
      },
      "poolformer_m36": {
        "cka": 0.022639654576778412,
        "acc": 82.1
      },
      "cait_s24_224": {
        "cka": 0.013127082027494907,
        "acc": 83.5
      },
      "mixer_b16": {
        "cka": 0.023799892514944077,
        "acc": 78.5
      },
      "vgg16_bn": {
        "cka": 0.04170879349112511,
        "acc": 73.4
      },
      "vgg19_bn": {
        "cka": 0.035116009414196014,
        "acc": 74.2
      }
    },
    "seed_42_n64": {
      "resnet18": {
        "cka": 0.16060654819011688,
        "acc": 71.5
      },
      "resnet34": {
        "cka": 0.17914022505283356,
        "acc": 75.1
      },
      "resnet50": {
        "cka": 0.16197116672992706,
        "acc": 79.8
      },
      "resnet101": {
        "cka": 0.1364317238330841,
        "acc": 81.5
      },
      "resnet152": {
        "cka": 0.1623281091451645,
        "acc": 82.0
      },
      "resnext50_32x4d": {
        "cka": 0.19510862231254578,
        "acc": 80.1
      },
      "resnext101_32x8d": {
        "cka": 0.221637561917305,
        "acc": 82.2
      },
      "wide_resnet50_2": {
        "cka": 0.17690131068229675,
        "acc": 81.6
      },
      "wide_resnet101_2": {
        "cka": 0.23062874376773834,
        "acc": 82.5
      },
      "densenet121": {
        "cka": 0.17107786238193512,
        "acc": 75.6
      },
      "densenet169": {
        "cka": 0.2433716356754303,
        "acc": 76.2
      },
      "densenet201": {
        "cka": 0.20646251738071442,
        "acc": 77.4
      },
      "efficientnet_b0": {
        "cka": 0.16058459877967834,
        "acc": 77.7
      },
      "efficientnet_b1": {
        "cka": 0.1835487186908722,
        "acc": 79.2
      },
      "efficientnet_b2": {
        "cka": 0.15494956076145172,
        "acc": 80.6
      },
      "efficientnet_b3": {
        "cka": 0.11478865891695023,
        "acc": 82.0
      },
      "efficientnet_b4": {
        "cka": 0.17243438959121704,
        "acc": 83.4
      },
      "efficientnetv2_s": {
        "cka": 0.13767997920513153,
        "acc": 83.9
      },
      "efficientnetv2_m": {
        "cka": 0.18187597393989563,
        "acc": 85.1
      },
      "mobilenetv2_100": {
        "cka": 0.14782528579235077,
        "acc": 72.9
      },
      "mobilenetv2_140": {
        "cka": 0.18373730778694153,
        "acc": 76.5
      },
      "mobilenetv3_large": {
        "cka": 0.09942512214183807,
        "acc": 75.8
      },
      "mobilenetv3_small": {
        "cka": 0.1576567441225052,
        "acc": 67.7
      },
      "mnasnet_100": {
        "cka": 0.20341996848583221,
        "acc": 74.7
      },
      "convnext_tiny": {
        "cka": 0.11045332252979279,
        "acc": 82.1
      },
      "convnext_small": {
        "cka": 0.0953470915555954,
        "acc": 83.1
      },
      "convnext_base": {
        "cka": 0.11270476877689362,
        "acc": 83.8
      },
      "convnext_large": {
        "cka": 0.10554905980825424,
        "acc": 84.3
      },
      "convnextv2_tiny": {
        "cka": 0.1582433581352234,
        "acc": 82.9
      },
      "convnextv2_base": {
        "cka": 0.15873606503009796,
        "acc": 84.9
      },
      "vit_tiny_patch16": {
        "cka": 0.10335741192102432,
        "acc": 75.5
      },
      "vit_small_patch16": {
        "cka": 0.12126677483320236,
        "acc": 81.4
      },
      "vit_base_patch16": {
        "cka": 0.14326849579811096,
        "acc": 84.0
      },
      "vit_base_patch32": {
        "cka": 0.10785622149705887,
        "acc": 80.7
      },
      "vit_large_patch16": {
        "cka": 0.10002001374959946,
        "acc": 85.8
      },
      "vit_small_patch16_dino": {
        "cka": 0.2020951211452484,
        "acc": 78.0
      },
      "swin_tiny": {
        "cka": 0.10766975581645966,
        "acc": 81.2
      },
      "swin_small": {
        "cka": 0.1197250559926033,
        "acc": 83.2
      },
      "swin_base": {
        "cka": 0.09090645611286163,
        "acc": 83.5
      },
      "deit_tiny": {
        "cka": 0.1578502207994461,
        "acc": 72.2
      },
      "deit_small": {
        "cka": 0.15589211881160736,
        "acc": 79.9
      },
      "deit_base": {
        "cka": 0.13450665771961212,
        "acc": 81.8
      },
      "deit3_small": {
        "cka": 0.20438449084758759,
        "acc": 81.4
      },
      "deit3_base": {
        "cka": 0.10546211898326874,
        "acc": 83.8
      },
      "deit3_large": {
        "cka": 0.06050937995314598,
        "acc": 84.9
      },
      "regnetx_016": {
        "cka": 0.19699323177337646,
        "acc": 73.0
      },
      "regnetx_032": {
        "cka": 0.2421768307685852,
        "acc": 75.2
      },
      "regnetx_064": {
        "cka": 0.26011598110198975,
        "acc": 76.4
      },
      "regnetx_160": {
        "cka": 0.24205294251441956,
        "acc": 79.7
      },
      "regnety_016": {
        "cka": 0.1933441460132599,
        "acc": 74.0
      },
      "regnety_032": {
        "cka": 0.12773801386356354,
        "acc": 76.6
      },
      "regnety_064": {
        "cka": 0.17912574112415314,
        "acc": 77.2
      },
      "regnety_160": {
        "cka": 0.15553033351898193,
        "acc": 80.4
      },
      "maxvit_tiny": {
        "cka": 0.1487048864364624,
        "acc": 83.4
      },
      "maxvit_small": {
        "cka": 0.07868115603923798,
        "acc": 84.5
      },
      "coatnet_0": {
        "cka": 0.11636712402105331,
        "acc": 82.4
      },
      "efficientformer_l1": {
        "cka": 0.17997367680072784,
        "acc": 80.2
      },
      "efficientformer_l3": {
        "cka": 0.09981271624565125,
        "acc": 82.4
      },
      "efficientformer_l7": {
        "cka": 0.07944367825984955,
        "acc": 83.3
      },
      "edgenext_small": {
        "cka": 0.17813077569007874,
        "acc": 81.1
      },
      "edgenext_base": {
        "cka": 0.19794459640979767,
        "acc": 83.3
      },
      "inception_v3": {
        "cka": 0.27003324031829834,
        "acc": 77.3
      },
      "inception_v4": {
        "cka": 0.16043777763843536,
        "acc": 80.2
      },
      "dpn68": {
        "cka": 0.1885548233985901,
        "acc": 76.3
      },
      "dpn92": {
        "cka": 0.17058846354484558,
        "acc": 79.5
      },
      "dpn131": {
        "cka": 0.14319606125354767,
        "acc": 79.8
      },
      "nasnetalarge": {
        "cka": 0.1784563809633255,
        "acc": 82.6
      },
      "senet154": {
        "cka": 0.14888083934783936,
        "acc": 81.3
      },
      "seresnext50_32x4d": {
        "cka": 0.2062121480703354,
        "acc": 79.9
      },
      "res2net50_26w_4s": {
        "cka": 0.1897946000099182,
        "acc": 78.0
      },
      "res2net101_26w_4s": {
        "cka": 0.13600854575634003,
        "acc": 79.2
      },
      "hrnet_w18": {
        "cka": 0.2257152497768402,
        "acc": 78.0
      },
      "hrnet_w32": {
        "cka": 0.2033454030752182,
        "acc": 78.4
      },
      "hrnet_w48": {
        "cka": 0.19753038883209229,
        "acc": 79.3
      },
      "ghostnet_100": {
        "cka": 0.13006046414375305,
        "acc": 74.0
      },
      "poolformer_s12": {
        "cka": 0.06926226615905762,
        "acc": 77.2
      },
      "poolformer_s24": {
        "cka": 0.14793729782104492,
        "acc": 80.3
      },
      "poolformer_s36": {
        "cka": 0.12477464973926544,
        "acc": 81.4
      },
      "poolformer_m36": {
        "cka": 0.17571114003658295,
        "acc": 82.1
      },
      "cait_s24_224": {
        "cka": 0.12940233945846558,
        "acc": 83.5
      },
      "mixer_b16": {
        "cka": 0.20055422186851501,
        "acc": 78.5
      },
      "vgg16_bn": {
        "cka": 0.2740912437438965,
        "acc": 73.4
      },
      "vgg19_bn": {
        "cka": 0.26514729857444763,
        "acc": 74.2
      }
    },
    "seed_42_n128": {
      "resnet18": {
        "cka": 0.08424606919288635,
        "acc": 71.5
      },
      "resnet34": {
        "cka": 0.10444684326648712,
        "acc": 75.1
      },
      "resnet50": {
        "cka": 0.07763873040676117,
        "acc": 79.8
      },
      "resnet101": {
        "cka": 0.07452789694070816,
        "acc": 81.5
      },
      "resnet152": {
        "cka": 0.07003502547740936,
        "acc": 82.0
      },
      "resnext50_32x4d": {
        "cka": 0.07900833338499069,
        "acc": 80.1
      },
      "resnext101_32x8d": {
        "cka": 0.11191914230585098,
        "acc": 82.2
      },
      "wide_resnet50_2": {
        "cka": 0.08432675153017044,
        "acc": 81.6
      },
      "wide_resnet101_2": {
        "cka": 0.12351848185062408,
        "acc": 82.5
      },
      "densenet121": {
        "cka": 0.10267461091279984,
        "acc": 75.6
      },
      "densenet169": {
        "cka": 0.12472521513700485,
        "acc": 76.2
      },
      "densenet201": {
        "cka": 0.10463734716176987,
        "acc": 77.4
      },
      "efficientnet_b0": {
        "cka": 0.07784967124462128,
        "acc": 77.7
      },
      "efficientnet_b1": {
        "cka": 0.0825018510222435,
        "acc": 79.2
      },
      "efficientnet_b2": {
        "cka": 0.07026281207799911,
        "acc": 80.6
      },
      "efficientnet_b3": {
        "cka": 0.07418682426214218,
        "acc": 82.0
      },
      "efficientnet_b4": {
        "cka": 0.08459945023059845,
        "acc": 83.4
      },
      "efficientnetv2_s": {
        "cka": 0.051159899681806564,
        "acc": 83.9
      },
      "efficientnetv2_m": {
        "cka": 0.0780482366681099,
        "acc": 85.1
      },
      "mobilenetv2_100": {
        "cka": 0.0770629420876503,
        "acc": 72.9
      },
      "mobilenetv2_140": {
        "cka": 0.09661322832107544,
        "acc": 76.5
      },
      "mobilenetv3_large": {
        "cka": 0.05284466594457626,
        "acc": 75.8
      },
      "mobilenetv3_small": {
        "cka": 0.07135426253080368,
        "acc": 67.7
      },
      "mnasnet_100": {
        "cka": 0.10144297778606415,
        "acc": 74.7
      },
      "convnext_tiny": {
        "cka": 0.07325639575719833,
        "acc": 82.1
      },
      "convnext_small": {
        "cka": 0.05283306911587715,
        "acc": 83.1
      },
      "convnext_base": {
        "cka": 0.05632796138525009,
        "acc": 83.8
      },
      "convnext_large": {
        "cka": 0.0568566732108593,
        "acc": 84.3
      },
      "convnextv2_tiny": {
        "cka": 0.0816597118973732,
        "acc": 82.9
      },
      "convnextv2_base": {
        "cka": 0.07123245298862457,
        "acc": 84.9
      },
      "vit_tiny_patch16": {
        "cka": 0.060531627386808395,
        "acc": 75.5
      },
      "vit_small_patch16": {
        "cka": 0.060899823904037476,
        "acc": 81.4
      },
      "vit_base_patch16": {
        "cka": 0.07433754950761795,
        "acc": 84.0
      },
      "vit_base_patch32": {
        "cka": 0.04920973628759384,
        "acc": 80.7
      },
      "vit_large_patch16": {
        "cka": 0.06445970386266708,
        "acc": 85.8
      },
      "vit_small_patch16_dino": {
        "cka": 0.10318932682275772,
        "acc": 78.0
      },
      "swin_tiny": {
        "cka": 0.07073799520730972,
        "acc": 81.2
      },
      "swin_small": {
        "cka": 0.05710890516638756,
        "acc": 83.2
      },
      "swin_base": {
        "cka": 0.04659956693649292,
        "acc": 83.5
      },
      "deit_tiny": {
        "cka": 0.07972809672355652,
        "acc": 72.2
      },
      "deit_small": {
        "cka": 0.0656495913863182,
        "acc": 79.9
      },
      "deit_base": {
        "cka": 0.0726531445980072,
        "acc": 81.8
      },
      "deit3_small": {
        "cka": 0.12901455163955688,
        "acc": 81.4
      },
      "deit3_base": {
        "cka": 0.05189577862620354,
        "acc": 83.8
      },
      "deit3_large": {
        "cka": 0.032383810728788376,
        "acc": 84.9
      },
      "regnetx_016": {
        "cka": 0.09930897504091263,
        "acc": 73.0
      },
      "regnetx_032": {
        "cka": 0.1410309374332428,
        "acc": 75.2
      },
      "regnetx_064": {
        "cka": 0.12270960956811905,
        "acc": 76.4
      },
      "regnetx_160": {
        "cka": 0.1270989328622818,
        "acc": 79.7
      },
      "regnety_016": {
        "cka": 0.09934066236019135,
        "acc": 74.0
      },
      "regnety_032": {
        "cka": 0.07020799815654755,
        "acc": 76.6
      },
      "regnety_064": {
        "cka": 0.08665195852518082,
        "acc": 77.2
      },
      "regnety_160": {
        "cka": 0.08635864406824112,
        "acc": 80.4
      },
      "maxvit_tiny": {
        "cka": 0.11615609377622604,
        "acc": 83.4
      },
      "maxvit_small": {
        "cka": 0.051239270716905594,
        "acc": 84.5
      },
      "coatnet_0": {
        "cka": 0.07202722132205963,
        "acc": 82.4
      },
      "efficientformer_l1": {
        "cka": 0.07882822304964066,
        "acc": 80.2
      },
      "efficientformer_l3": {
        "cka": 0.04784531891345978,
        "acc": 82.4
      },
      "efficientformer_l7": {
        "cka": 0.047652266919612885,
        "acc": 83.3
      },
      "edgenext_small": {
        "cka": 0.0881887674331665,
        "acc": 81.1
      },
      "edgenext_base": {
        "cka": 0.09474015980958939,
        "acc": 83.3
      },
      "inception_v3": {
        "cka": 0.14825698733329773,
        "acc": 77.3
      },
      "inception_v4": {
        "cka": 0.10314968973398209,
        "acc": 80.2
      },
      "dpn68": {
        "cka": 0.09675141423940659,
        "acc": 76.3
      },
      "dpn92": {
        "cka": 0.08713880926370621,
        "acc": 79.5
      },
      "dpn131": {
        "cka": 0.06866870075464249,
        "acc": 79.8
      },
      "nasnetalarge": {
        "cka": 0.08921079337596893,
        "acc": 82.6
      },
      "senet154": {
        "cka": 0.08564912527799606,
        "acc": 81.3
      },
      "seresnext50_32x4d": {
        "cka": 0.1192559078335762,
        "acc": 79.9
      },
      "res2net50_26w_4s": {
        "cka": 0.09210649877786636,
        "acc": 78.0
      },
      "res2net101_26w_4s": {
        "cka": 0.07315865904092789,
        "acc": 79.2
      },
      "hrnet_w18": {
        "cka": 0.11659198254346848,
        "acc": 78.0
      },
      "hrnet_w32": {
        "cka": 0.11286618560552597,
        "acc": 78.4
      },
      "hrnet_w48": {
        "cka": 0.09257722645998001,
        "acc": 79.3
      },
      "ghostnet_100": {
        "cka": 0.05553562566637993,
        "acc": 74.0
      },
      "poolformer_s12": {
        "cka": 0.02961456961929798,
        "acc": 77.2
      },
      "poolformer_s24": {
        "cka": 0.08530771732330322,
        "acc": 80.3
      },
      "poolformer_s36": {
        "cka": 0.05706499144434929,
        "acc": 81.4
      },
      "poolformer_m36": {
        "cka": 0.08609480410814285,
        "acc": 82.1
      },
      "cait_s24_224": {
        "cka": 0.0582689605653286,
        "acc": 83.5
      },
      "mixer_b16": {
        "cka": 0.09026936441659927,
        "acc": 78.5
      },
      "vgg16_bn": {
        "cka": 0.15168829262256622,
        "acc": 73.4
      },
      "vgg19_bn": {
        "cka": 0.14349812269210815,
        "acc": 74.2
      }
    },
    "seed_42_n256": {
      "resnet18": {
        "cka": 0.0411575585603714,
        "acc": 71.5
      },
      "resnet34": {
        "cka": 0.05204709246754646,
        "acc": 75.1
      },
      "resnet50": {
        "cka": 0.04080896079540253,
        "acc": 79.8
      },
      "resnet101": {
        "cka": 0.03814484179019928,
        "acc": 81.5
      },
      "resnet152": {
        "cka": 0.032146163284778595,
        "acc": 82.0
      },
      "resnext50_32x4d": {
        "cka": 0.03680969402194023,
        "acc": 80.1
      },
      "resnext101_32x8d": {
        "cka": 0.0426097996532917,
        "acc": 82.2
      },
      "wide_resnet50_2": {
        "cka": 0.044333167374134064,
        "acc": 81.6
      },
      "wide_resnet101_2": {
        "cka": 0.06689010560512543,
        "acc": 82.5
      },
      "densenet121": {
        "cka": 0.048140645027160645,
        "acc": 75.6
      },
      "densenet169": {
        "cka": 0.0549447126686573,
        "acc": 76.2
      },
      "densenet201": {
        "cka": 0.052631985396146774,
        "acc": 77.4
      },
      "efficientnet_b0": {
        "cka": 0.04550780728459358,
        "acc": 77.7
      },
      "efficientnet_b1": {
        "cka": 0.03840021416544914,
        "acc": 79.2
      },
      "efficientnet_b2": {
        "cka": 0.040988340973854065,
        "acc": 80.6
      },
      "efficientnet_b3": {
        "cka": 0.030480317771434784,
        "acc": 82.0
      },
      "efficientnet_b4": {
        "cka": 0.047508254647254944,
        "acc": 83.4
      },
      "efficientnetv2_s": {
        "cka": 0.023850280791521072,
        "acc": 83.9
      },
      "efficientnetv2_m": {
        "cka": 0.03261986002326012,
        "acc": 85.1
      },
      "mobilenetv2_100": {
        "cka": 0.03791353851556778,
        "acc": 72.9
      },
      "mobilenetv2_140": {
        "cka": 0.05796134099364281,
        "acc": 76.5
      },
      "mobilenetv3_large": {
        "cka": 0.028208190575242043,
        "acc": 75.8
      },
      "mobilenetv3_small": {
        "cka": 0.037798069417476654,
        "acc": 67.7
      },
      "mnasnet_100": {
        "cka": 0.04762740060687065,
        "acc": 74.7
      },
      "convnext_tiny": {
        "cka": 0.03062400035560131,
        "acc": 82.1
      },
      "convnext_small": {
        "cka": 0.025297846645116806,
        "acc": 83.1
      },
      "convnext_base": {
        "cka": 0.02598661184310913,
        "acc": 83.8
      },
      "convnext_large": {
        "cka": 0.03588038682937622,
        "acc": 84.3
      },
      "convnextv2_tiny": {
        "cka": 0.03932904079556465,
        "acc": 82.9
      },
      "convnextv2_base": {
        "cka": 0.033160388469696045,
        "acc": 84.9
      },
      "vit_tiny_patch16": {
        "cka": 0.03428688645362854,
        "acc": 75.5
      },
      "vit_small_patch16": {
        "cka": 0.029203403741121292,
        "acc": 81.4
      },
      "vit_base_patch16": {
        "cka": 0.0358305461704731,
        "acc": 84.0
      },
      "vit_base_patch32": {
        "cka": 0.02496250346302986,
        "acc": 80.7
      },
      "vit_large_patch16": {
        "cka": 0.0373084656894207,
        "acc": 85.8
      },
      "vit_small_patch16_dino": {
        "cka": 0.05581999570131302,
        "acc": 78.0
      },
      "swin_tiny": {
        "cka": 0.0333583801984787,
        "acc": 81.2
      },
      "swin_small": {
        "cka": 0.03929337114095688,
        "acc": 83.2
      },
      "swin_base": {
        "cka": 0.028397370129823685,
        "acc": 83.5
      },
      "deit_tiny": {
        "cka": 0.036327388137578964,
        "acc": 72.2
      },
      "deit_small": {
        "cka": 0.0359407439827919,
        "acc": 79.9
      },
      "deit_base": {
        "cka": 0.03443450480699539,
        "acc": 81.8
      },
      "deit3_small": {
        "cka": 0.056191585958004,
        "acc": 81.4
      },
      "deit3_base": {
        "cka": 0.03589970991015434,
        "acc": 83.8
      },
      "deit3_large": {
        "cka": 0.021556463092565536,
        "acc": 84.9
      },
      "regnetx_016": {
        "cka": 0.050402019172906876,
        "acc": 73.0
      },
      "regnetx_032": {
        "cka": 0.057180434465408325,
        "acc": 75.2
      },
      "regnetx_064": {
        "cka": 0.07133752107620239,
        "acc": 76.4
      },
      "regnetx_160": {
        "cka": 0.0682230144739151,
        "acc": 79.7
      },
      "regnety_016": {
        "cka": 0.05311639979481697,
        "acc": 74.0
      },
      "regnety_032": {
        "cka": 0.03584920987486839,
        "acc": 76.6
      },
      "regnety_064": {
        "cka": 0.044601984322071075,
        "acc": 77.2
      },
      "regnety_160": {
        "cka": 0.052031077444553375,
        "acc": 80.4
      },
      "maxvit_tiny": {
        "cka": 0.035893116146326065,
        "acc": 83.4
      },
      "maxvit_small": {
        "cka": 0.04165136069059372,
        "acc": 84.5
      },
      "coatnet_0": {
        "cka": 0.029821135103702545,
        "acc": 82.4
      },
      "efficientformer_l1": {
        "cka": 0.0446893647313118,
        "acc": 80.2
      },
      "efficientformer_l3": {
        "cka": 0.016226457431912422,
        "acc": 82.4
      },
      "efficientformer_l7": {
        "cka": 0.02935008704662323,
        "acc": 83.3
      },
      "edgenext_small": {
        "cka": 0.04130035638809204,
        "acc": 81.1
      },
      "edgenext_base": {
        "cka": 0.04306279495358467,
        "acc": 83.3
      },
      "inception_v3": {
        "cka": 0.08813176304101944,
        "acc": 77.3
      },
      "inception_v4": {
        "cka": 0.03807296231389046,
        "acc": 80.2
      },
      "dpn68": {
        "cka": 0.05227956175804138,
        "acc": 76.3
      },
      "dpn92": {
        "cka": 0.04965002462267876,
        "acc": 79.5
      },
      "dpn131": {
        "cka": 0.04033692553639412,
        "acc": 79.8
      },
      "nasnetalarge": {
        "cka": 0.04492303356528282,
        "acc": 82.6
      },
      "senet154": {
        "cka": 0.04635721817612648,
        "acc": 81.3
      },
      "seresnext50_32x4d": {
        "cka": 0.050022367388010025,
        "acc": 79.9
      },
      "res2net50_26w_4s": {
        "cka": 0.04479951411485672,
        "acc": 78.0
      },
      "res2net101_26w_4s": {
        "cka": 0.05323491618037224,
        "acc": 79.2
      },
      "hrnet_w18": {
        "cka": 0.06064074859023094,
        "acc": 78.0
      },
      "hrnet_w32": {
        "cka": 0.05304686725139618,
        "acc": 78.4
      },
      "hrnet_w48": {
        "cka": 0.05158607289195061,
        "acc": 79.3
      },
      "ghostnet_100": {
        "cka": 0.029351714998483658,
        "acc": 74.0
      },
      "poolformer_s12": {
        "cka": 0.03354125842452049,
        "acc": 77.2
      },
      "poolformer_s24": {
        "cka": 0.04013020545244217,
        "acc": 80.3
      },
      "poolformer_s36": {
        "cka": 0.02219253033399582,
        "acc": 81.4
      },
      "poolformer_m36": {
        "cka": 0.04213271290063858,
        "acc": 82.1
      },
      "cait_s24_224": {
        "cka": 0.03334389999508858,
        "acc": 83.5
      },
      "mixer_b16": {
        "cka": 0.04008748382329941,
        "acc": 78.5
      },
      "vgg16_bn": {
        "cka": 0.07922856509685516,
        "acc": 73.4
      },
      "vgg19_bn": {
        "cka": 0.07013595104217529,
        "acc": 74.2
      }
    },
    "seed_42_n1024": {
      "resnet18": {
        "cka": 0.01091722585260868,
        "acc": 71.5
      },
      "resnet34": {
        "cka": 0.01155068539083004,
        "acc": 75.1
      },
      "resnet50": {
        "cka": 0.010328537784516811,
        "acc": 79.8
      },
      "resnet101": {
        "cka": 0.009682366624474525,
        "acc": 81.5
      },
      "resnet152": {
        "cka": 0.00920757744461298,
        "acc": 82.0
      },
      "resnext50_32x4d": {
        "cka": 0.01013685017824173,
        "acc": 80.1
      },
      "resnext101_32x8d": {
        "cka": 0.010682879015803337,
        "acc": 82.2
      },
      "wide_resnet50_2": {
        "cka": 0.011438562534749508,
        "acc": 81.6
      },
      "wide_resnet101_2": {
        "cka": 0.01423877477645874,
        "acc": 82.5
      },
      "densenet121": {
        "cka": 0.012646570801734924,
        "acc": 75.6
      },
      "densenet169": {
        "cka": 0.019101029261946678,
        "acc": 76.2
      },
      "densenet201": {
        "cka": 0.011604306288063526,
        "acc": 77.4
      },
      "efficientnet_b0": {
        "cka": 0.012942097149789333,
        "acc": 77.7
      },
      "efficientnet_b1": {
        "cka": 0.010427858680486679,
        "acc": 79.2
      },
      "efficientnet_b2": {
        "cka": 0.00701844273135066,
        "acc": 80.6
      },
      "efficientnet_b3": {
        "cka": 0.007535594515502453,
        "acc": 82.0
      },
      "efficientnet_b4": {
        "cka": 0.011644269339740276,
        "acc": 83.4
      },
      "efficientnetv2_s": {
        "cka": 0.007154386956244707,
        "acc": 83.9
      },
      "efficientnetv2_m": {
        "cka": 0.01089375652372837,
        "acc": 85.1
      },
      "mobilenetv2_100": {
        "cka": 0.010086230002343655,
        "acc": 72.9
      },
      "mobilenetv2_140": {
        "cka": 0.01477977354079485,
        "acc": 76.5
      },
      "mobilenetv3_large": {
        "cka": 0.00643297890201211,
        "acc": 75.8
      },
      "mobilenetv3_small": {
        "cka": 0.009512748569250107,
        "acc": 67.7
      },
      "mnasnet_100": {
        "cka": 0.010377084836363792,
        "acc": 74.7
      },
      "convnext_tiny": {
        "cka": 0.00806225836277008,
        "acc": 82.1
      },
      "convnext_small": {
        "cka": 0.006708930712193251,
        "acc": 83.1
      },
      "convnext_base": {
        "cka": 0.006717852782458067,
        "acc": 83.8
      },
      "convnext_large": {
        "cka": 0.007422993890941143,
        "acc": 84.3
      },
      "convnextv2_tiny": {
        "cka": 0.009622158482670784,
        "acc": 82.9
      },
      "convnextv2_base": {
        "cka": 0.008812207728624344,
        "acc": 84.9
      },
      "vit_tiny_patch16": {
        "cka": 0.008685753680765629,
        "acc": 75.5
      },
      "vit_small_patch16": {
        "cka": 0.012291228398680687,
        "acc": 81.4
      },
      "vit_base_patch16": {
        "cka": 0.009357494302093983,
        "acc": 84.0
      },
      "vit_base_patch32": {
        "cka": 0.0070322658866643906,
        "acc": 80.7
      },
      "vit_large_patch16": {
        "cka": 0.010180261917412281,
        "acc": 85.8
      },
      "vit_small_patch16_dino": {
        "cka": 0.017801620066165924,
        "acc": 78.0
      },
      "swin_tiny": {
        "cka": 0.006479915697127581,
        "acc": 81.2
      },
      "swin_small": {
        "cka": 0.00948601495474577,
        "acc": 83.2
      },
      "swin_base": {
        "cka": 0.0072584995068609715,
        "acc": 83.5
      },
      "deit_tiny": {
        "cka": 0.00846545398235321,
        "acc": 72.2
      },
      "deit_small": {
        "cka": 0.008684780448675156,
        "acc": 79.9
      },
      "deit_base": {
        "cka": 0.010403294116258621,
        "acc": 81.8
      },
      "deit3_small": {
        "cka": 0.01449981052428484,
        "acc": 81.4
      },
      "deit3_base": {
        "cka": 0.010041405446827412,
        "acc": 83.8
      },
      "deit3_large": {
        "cka": 0.006100500002503395,
        "acc": 84.9
      },
      "regnetx_016": {
        "cka": 0.0133493198081851,
        "acc": 73.0
      },
      "regnetx_032": {
        "cka": 0.016806628555059433,
        "acc": 75.2
      },
      "regnetx_064": {
        "cka": 0.016134710982441902,
        "acc": 76.4
      },
      "regnetx_160": {
        "cka": 0.01775040291249752,
        "acc": 79.7
      },
      "regnety_016": {
        "cka": 0.014249640516936779,
        "acc": 74.0
      },
      "regnety_032": {
        "cka": 0.008533389307558537,
        "acc": 76.6
      },
      "regnety_064": {
        "cka": 0.011932877823710442,
        "acc": 77.2
      },
      "regnety_160": {
        "cka": 0.012404696084558964,
        "acc": 80.4
      },
      "maxvit_tiny": {
        "cka": 0.008858300745487213,
        "acc": 83.4
      },
      "maxvit_small": {
        "cka": 0.0059776464477181435,
        "acc": 84.5
      },
      "coatnet_0": {
        "cka": 0.00757747795432806,
        "acc": 82.4
      },
      "efficientformer_l1": {
        "cka": 0.012176891788840294,
        "acc": 80.2
      },
      "efficientformer_l3": {
        "cka": 0.0050201560370624065,
        "acc": 82.4
      },
      "efficientformer_l7": {
        "cka": 0.007464950438588858,
        "acc": 83.3
      },
      "edgenext_small": {
        "cka": 0.009262495674192905,
        "acc": 81.1
      },
      "edgenext_base": {
        "cka": 0.011209369637072086,
        "acc": 83.3
      },
      "inception_v3": {
        "cka": 0.02533823251724243,
        "acc": 77.3
      },
      "inception_v4": {
        "cka": 0.011861461214721203,
        "acc": 80.2
      },
      "dpn68": {
        "cka": 0.011962132528424263,
        "acc": 76.3
      },
      "dpn92": {
        "cka": 0.010638161562383175,
        "acc": 79.5
      },
      "dpn131": {
        "cka": 0.008937115781009197,
        "acc": 79.8
      },
      "nasnetalarge": {
        "cka": 0.01230977289378643,
        "acc": 82.6
      },
      "senet154": {
        "cka": 0.011529618874192238,
        "acc": 81.3
      },
      "seresnext50_32x4d": {
        "cka": 0.011529580689966679,
        "acc": 79.9
      },
      "res2net50_26w_4s": {
        "cka": 0.012322732247412205,
        "acc": 78.0
      },
      "res2net101_26w_4s": {
        "cka": 0.009289032779633999,
        "acc": 79.2
      },
      "hrnet_w18": {
        "cka": 0.016096584498882294,
        "acc": 78.0
      },
      "hrnet_w32": {
        "cka": 0.014292779378592968,
        "acc": 78.4
      },
      "hrnet_w48": {
        "cka": 0.014445441775023937,
        "acc": 79.3
      },
      "ghostnet_100": {
        "cka": 0.010417688637971878,
        "acc": 74.0
      },
      "poolformer_s12": {
        "cka": 0.004292105324566364,
        "acc": 77.2
      },
      "poolformer_s24": {
        "cka": 0.009944310411810875,
        "acc": 80.3
      },
      "poolformer_s36": {
        "cka": 0.0046102069318294525,
        "acc": 81.4
      },
      "poolformer_m36": {
        "cka": 0.008133689872920513,
        "acc": 82.1
      },
      "cait_s24_224": {
        "cka": 0.007735429797321558,
        "acc": 83.5
      },
      "mixer_b16": {
        "cka": 0.009993426501750946,
        "acc": 78.5
      },
      "vgg16_bn": {
        "cka": 0.022437214851379395,
        "acc": 73.4
      },
      "vgg19_bn": {
        "cka": 0.01753658428788185,
        "acc": 74.2
      }
    }
  },
  "pairwise_tau": {
    "42_vs_123": {
      "tau": 0.6109315310020569,
      "p": 2.9315490813570913e-16,
      "n": 83
    },
    "42_vs_456": {
      "tau": 0.599177196591243,
      "p": 1.0678210017112001e-15,
      "n": 83
    },
    "42_vs_789": {
      "tau": 0.6550102850426094,
      "p": 1.850985848602892e-18,
      "n": 83
    },
    "42_vs_2024": {
      "tau": 0.6461945342344989,
      "p": 5.239361954975293e-18,
      "n": 83
    },
    "123_vs_456": {
      "tau": 0.6262121657361152,
      "p": 5.265371834139212e-17,
      "n": 83
    },
    "123_vs_789": {
      "tau": 0.6079929473993534,
      "p": 4.0592047041904243e-16,
      "n": 83
    },
    "123_vs_2024": {
      "tau": 0.6109315310020569,
      "p": 2.9315490813570913e-16,
      "n": 83
    },
    "456_vs_789": {
      "tau": 0.6573611519247722,
      "p": 1.399247287676532e-18,
      "n": 83
    },
    "456_vs_2024": {
      "tau": 0.5980017631501615,
      "p": 1.2135448757886855e-15,
      "n": 83
    },
    "789_vs_2024": {
      "tau": 0.6550102850426094,
      "p": 1.850985848602892e-18,
      "n": 83
    }
  },
  "config": {
    "seeds": [
      42,
      123,
      456,
      789,
      2024
    ],
    "probe_sizes": [
      64,
      128,
      256,
      512,
      1024
    ],
    "num_candidates": 83,
    "teacher": "dinov2_small",
    "elapsed_seconds": 1284.3161952495575
  }
}